rosmock/__init__.py
rosmock/example.py
rosmock-0.0.1.dist-info/licenses/LICENSE
rosmock-0.0.1.dist-info/METADATA
rosmock-0.0.1.dist-info/WHEEL
rosmock-0.0.1.dist-info/top_level.txt
rosmock-0.0.1.dist-info/RECORD
